cvxoptklu/__init__.py
cvxoptklu/_version.py
cvxoptklu/klu.cpython-36m-darwin.so
cvxoptklu-1.2.1.dist-info/METADATA
cvxoptklu-1.2.1.dist-info/RECORD
cvxoptklu-1.2.1.dist-info/WHEEL
cvxoptklu-1.2.1.dist-info/top_level.txt
