Metadata-Version: 2.1
Name: cvxoptklu
Version: 1.2.1
Summary: CVXOPT KLU Add-on
Home-page: http://cvxopt.org
Author: M. Andersen, J. Dahl, and L. Vandenberghe
Author-email: martin.skovgaard.andersen@gmail.com, dahl.joachim@gmail.com, vandenbe@ee.ucla.edu
License: GNU GPL version 3
Platform: UNKNOWN
Classifier: Development Status :: 5 - Production/Stable
Classifier: Intended Audience :: Science/Research
Classifier: License :: OSI Approved :: GNU General Public License v3 (GPLv3)
Classifier: Operating System :: OS Independent
Classifier: Programming Language :: C
Classifier: Programming Language :: Python
Classifier: Programming Language :: Python :: 3
Classifier: Topic :: Scientific/Engineering
